itple/__init__.py
itple/__version__.py
itple/base.py
itple/live.py
itple/firmware/Itple_Python_firmware_V1.0.0/Itple_Python_firmware_V1.0.0.ino
itple-0.0.2.dist-info/METADATA
itple-0.0.2.dist-info/WHEEL
itple-0.0.2.dist-info/licenses/LICENSE
itple-0.0.2.dist-info/RECORD
