Metadata-Version: 2.4
Name: itple
Version: 0.0.2
Summary: A Python module to generate Arduino code for Itple contents.
Author-email: ITPLE <itple@itpleinfo.com>
License-File: LICENSE
Requires-Python: >=3.8
Requires-Dist: pyserial>=3.0
